rlenv/__init__.py
rlenv/envs/__init__.py
rlenv/envs/eplus/__init__.py
rlenv/envs/wall/__init__.py
rlenv/envs/wall/core.py
rlenv/envs/wall/tests/__init__.py
rlenv/envs/wall/tests/test_wall_env.py
rlenv/sed/__init__.py
rlenv/sed/eplus.py
rlenv/sed/wall.py
rlenv/sed/systems/__init__.py
rlenv/weather/__init__.py
rlenv/weather/forecast/__init__.py
rlenv/weather/forecast/bogus.py
rlenv/weather/generator/__init__.py
rlenv/weather/generator/brownianbridge.py
rlenv/weather/generator/toysine.py
rlenv/weather/generator/toysine2.py
rlenv-1.1.dev2.dist-info/AUTHORS
rlenv-1.1.dev2.dist-info/LICENSE
rlenv-1.1.dev2.dist-info/METADATA
rlenv-1.1.dev2.dist-info/WHEEL
rlenv-1.1.dev2.dist-info/top_level.txt
rlenv-1.1.dev2.dist-info/RECORD
