Metadata-Version: 2.1
Name: rlenv
Version: 1.1.dev2
Summary: Accenta.AI Gym Environement
Home-page: 
Download-URL: 
Author: Jérémie DECOCK
Author-email: jeremie.decock@accenta.ai
Maintainer: Jérémie DECOCK
Maintainer-email: jeremie.decock@accenta.ai
Keywords: rlenv
Classifier: Development Status :: 4 - Beta
Classifier: Intended Audience :: Developers
Classifier: Natural Language :: English
Classifier: Operating System :: OS Independent
Classifier: Programming Language :: Python :: 3
Classifier: Topic :: Software Development :: Libraries
Classifier: Topic :: Software Development :: Libraries :: Python Modules
Classifier: Topic :: Software Development :: Libraries :: Application Frameworks
License-File: LICENSE
License-File: AUTHORS
Requires-Dist: coverage
Requires-Dist: gym
Requires-Dist: matplotlib
Requires-Dist: numpy
Requires-Dist: pandas
Requires-Dist: pytest
Requires-Dist: pyyaml
Requires-Dist: scipy
Requires-Dist: seaborn
Requires-Dist: setuptools
Requires-Dist: Sphinx
Requires-Dist: sphinx-gallery
Requires-Dist: sphinx-rtd-theme
